[
    {
        "booking_date": 1461888000000,
        "check_in_date": 1609718400000,
        "check_out_date": 1609804800000,
        "checked_in": "No",
        "confirmation_code": "FSB6ZYBGU1",
        "customer_id": "6aa95d0f-d71a-4b11-8889-0920e3d07038",
        "flight_booking_id": "6ddc910c-1852-4d2c-a994-b8c99bfa8f3c",
        "id": "e1c21595-a7e7-4046-b14c-568d29e4a0bf",
        "location": "London",
        "num_adults": 2,
        "num_children": 2,
        "payment_method": "PayPal",
        "room_type": "Single",
        "sales_agent_id": "2b0e08a1-b84e-4619-ac2d-88b101c24bf4",
        "status": "Pending",
        "total_price": 890.2369776225
    },
    {
        "booking_date": 1338422400000,
        "check_in_date": 1609718400000,
        "check_out_date": 1610236800000,
        "checked_in": "No",
        "confirmation_code": "QA7A61JKZE",
        "customer_id": "fbc0e8d8-691c-450b-9268-8ac066029efd",
        "flight_booking_id": "45fc7870-2dc6-4845-9dec-1208ce469bbe",
        "id": "ad90f248-4d0c-431b-82f9-50794d00f775",
        "location": "Cancun",
        "num_adults": 4,
        "num_children": 1,
        "payment_method": "Bank transfer",
        "room_type": "Double",
        "sales_agent_id": "75c9a9e1-d645-45d2-9f18-f6ed1c622a7c",
        "status": "Confirmed",
        "total_price": 535.3880858606
    },
    {
        "booking_date": 1667260800000,
        "check_in_date": 1609718400000,
        "check_out_date": 1609977600000,
        "checked_in": "Yes",
        "confirmation_code": "89BGVQXXHU",
        "customer_id": "c7b91628-ceaf-4164-a152-7b13e644220a",
        "flight_booking_id": "a7a05a8e-f0a9-4a3e-8939-8ee15cbbb5ba",
        "id": "849f351c-a8fc-4b82-bcb3-04c0d85b3f18",
        "location": "Cancun",
        "num_adults": 1,
        "num_children": 0,
        "payment_method": "Debit card",
        "room_type": "Family",
        "sales_agent_id": "d84a1475-c0f3-472f-bf99-b4ef3f3cc8d9",
        "status": "Cancelled",
        "total_price": 406.7496190494
    },
    {
        "booking_date": 1624492800000,
        "check_in_date": 1609718400000,
        "check_out_date": 1610236800000,
        "checked_in": "No",
        "confirmation_code": "3EZB6IATT8",
        "customer_id": "ebce5982-80fa-45bc-96e3-432782e32736",
        "flight_booking_id": "a7a05a8e-f0a9-4a3e-8939-8ee15cbbb5ba",
        "id": "979e967f-91fe-4d8d-a04a-cf3131f1459b",
        "location": "Maldives",
        "num_adults": 1,
        "num_children": 0,
        "payment_method": "Credit card",
        "room_type": "Family",
        "sales_agent_id": "03aaba71-ed56-4f4b-8cd4-21bd3d654051",
        "status": "Cancelled",
        "total_price": 916.8577522468
    }
]